<?xml version="1.0" encoding="utf-8"?>
<clothing-items>
 <clothing>
  <id>
   513385663
  </id>
  <name>
   Reebok Sweater H-3740
  </name>
  <category>
   Sweater
  </category>
  <size>
   XL
  </size>
  <color>
   Зеленый
  </color>
  <material>
   Кожа
  </material>
  <price>
   999584
  </price>
  <rating>
   3.07
  </rating>
  <reviews>
   976350
  </reviews>
  <new>
   -
  </new>
 </clothing>
 <clothing>
  <id>
   940265320
  </id>
  <name>
   Addidas Hat W-3876
  </name>
  <category>
   Hat
  </category>
  <size>
   XXL
  </size>
  <color>
   Желтый
  </color>
  <material>
   Шелк
  </material>
  <price>
   335775
  </price>
  <rating>
   3.0
  </rating>
  <reviews>
   202157
  </reviews>
  <new>
   -
  </new>
  <exclusive>
   no
  </exclusive>
 </clothing>
 <clothing>
  <id>
   221457542
  </id>
  <name>
   Nike Umbrellas R-7790
  </name>
  <category>
   Umbrellas
  </category>
  <size>
   XXL
  </size>
  <color>
   Зеленый
  </color>
  <material>
   Вискоза
  </material>
  <price>
   428764
  </price>
  <rating>
   2.24
  </rating>
  <reviews>
   728868
  </reviews>
  <new>
   +
  </new>
  <exclusive>
   no
  </exclusive>
 </clothing>
 <clothing>
  <id>
   957456459
  </id>
  <name>
   DC Handbags O-5987
  </name>
  <category>
   Handbags
  </category>
  <size>
   S
  </size>
  <color>
   Оранжевый
  </color>
  <material>
   Вискоза
  </material>
  <price>
   676404
  </price>
  <rating>
   3.69
  </rating>
  <reviews>
   852966
  </reviews>
  <new>
   -
  </new>
  <sporty>
   yes
  </sporty>
 </clothing>
 <clothing>
  <id>
   820801472
  </id>
  <name>
   Addidas Hat P-3354
  </name>
  <category>
   Hat
  </category>
  <size>
   S
  </size>
  <color>
   Красный
  </color>
  <material>
   Кожа
  </material>
  <price>
   890500
  </price>
  <rating>
   1.6
  </rating>
  <reviews>
   707870
  </reviews>
  <new>
   -
  </new>
  <sporty>
   no
  </sporty>
 </clothing>
 <clothing>
  <id>
   832743460
  </id>
  <name>
   Converse Belts O-6604
  </name>
  <category>
   Belts
  </category>
  <size>
   M
  </size>
  <color>
   Фиолетовый
  </color>
  <material>
   Шерсть
  </material>
  <price>
   794930
  </price>
  <rating>
   3.86
  </rating>
  <reviews>
   145301
  </reviews>
  <new>
   -
  </new>
  <exclusive>
   yes
  </exclusive>
 </clothing>
 <clothing>
  <id>
   751802161
  </id>
  <name>
   Under Armour Hat K-2894
  </name>
  <category>
   Hat
  </category>
  <size>
   L
  </size>
  <color>
   Синий
  </color>
  <material>
   Нейлон
  </material>
  <price>
   264390
  </price>
  <rating>
   2.23
  </rating>
  <reviews>
   14181
  </reviews>
  <new>
   -
  </new>
  <exclusive>
   no
  </exclusive>
  <sporty>
   yes
  </sporty>
 </clothing>
 <clothing>
  <id>
   723411114
  </id>
  <name>
   Asics Dress S-2606
  </name>
  <category>
   Dress
  </category>
  <size>
   XL
  </size>
  <color>
   Фиолетовый
  </color>
  <material>
   Лен
  </material>
  <price>
   926000
  </price>
  <rating>
   3.59
  </rating>
  <reviews>
   381755
  </reviews>
  <new>
   +
  </new>
 </clothing>
 <clothing>
  <id>
   964731557
  </id>
  <name>
   PleinSport Handbags K-5918
  </name>
  <category>
   Handbags
  </category>
  <size>
   S
  </size>
  <color>
   Красный
  </color>
  <material>
   Хлопок
  </material>
  <price>
   901059
  </price>
  <rating>
   1.6
  </rating>
  <reviews>
   545840
  </reviews>
  <sporty>
   yes
  </sporty>
 </clothing>
 <clothing>
  <id>
   798130515
  </id>
  <name>
   PleinSport T-shirt F-3368
  </name>
  <category>
   T-shirt
  </category>
  <size>
   XXL
  </size>
  <color>
   Желтый
  </color>
  <material>
   Лен
  </material>
  <price>
   857374
  </price>
  <rating>
   4.49
  </rating>
  <reviews>
   661406
  </reviews>
 </clothing>
 <clothing>
  <id>
   851409143
  </id>
  <name>
   Brooks Gloves C-1609
  </name>
  <category>
   Gloves
  </category>
  <size>
   XL
  </size>
  <color>
   Красный
  </color>
  <material>
   Вискоза
  </material>
  <price>
   315928
  </price>
  <rating>
   2.58
  </rating>
  <reviews>
   337209
  </reviews>
  <new>
   +
  </new>
  <exclusive>
   yes
  </exclusive>
  <sporty>
   no
  </sporty>
 </clothing>
 <clothing>
  <id>
   537588517
  </id>
  <name>
   Vans Hat A-8287
  </name>
  <category>
   Hat
  </category>
  <size>
   XXL
  </size>
  <color>
   Оранжевый
  </color>
  <material>
   Лен
  </material>
  <price>
   648218
  </price>
  <rating>
   3.31
  </rating>
  <reviews>
   855319
  </reviews>
  <new>
   +
  </new>
 </clothing>
 <clothing>
  <id>
   719873737
  </id>
  <name>
   Addidas Socks S-5935
  </name>
  <category>
   Socks
  </category>
  <size>
   XL
  </size>
  <color>
   Красный
  </color>
  <material>
   Шелк
  </material>
  <price>
   555950
  </price>
  <rating>
   3.61
  </rating>
  <reviews>
   356202
  </reviews>
  <exclusive>
   no
  </exclusive>
  <sporty>
   yes
  </sporty>
 </clothing>
 <clothing>
  <id>
   109810231
  </id>
  <name>
   Reebok Socks S-4487
  </name>
  <category>
   Socks
  </category>
  <size>
   XXL
  </size>
  <color>
   Красный
  </color>
  <material>
   Полиэстер
  </material>
  <price>
   752272
  </price>
  <rating>
   2.22
  </rating>
  <reviews>
   50011
  </reviews>
 </clothing>
 <clothing>
  <id>
   630089115
  </id>
  <name>
   Vans Gloves Y-6999
  </name>
  <category>
   Gloves
  </category>
  <size>
   XL
  </size>
  <color>
   Голубой
  </color>
  <material>
   Вискоза
  </material>
  <price>
   334540
  </price>
  <rating>
   4.69
  </rating>
  <reviews>
   583120
  </reviews>
  <new>
   -
  </new>
  <exclusive>
   no
  </exclusive>
 </clothing>
 <clothing>
  <id>
   538048399
  </id>
  <name>
   Lacoste Dress Z-7738
  </name>
  <category>
   Dress
  </category>
  <size>
   L
  </size>
  <color>
   Синий
  </color>
  <material>
   Вискоза
  </material>
  <price>
   379214
  </price>
  <rating>
   1.25
  </rating>
  <reviews>
   876028
  </reviews>
  <new>
   -
  </new>
  <sporty>
   no
  </sporty>
 </clothing>
 <clothing>
  <id>
   922172976
  </id>
  <name>
   Nike Sweater A-4167
  </name>
  <category>
   Sweater
  </category>
  <size>
   XL
  </size>
  <color>
   Голубой
  </color>
  <material>
   Хлопок
  </material>
  <price>
   373210
  </price>
  <rating>
   3.37
  </rating>
  <reviews>
   794997
  </reviews>
  <exclusive>
   yes
  </exclusive>
 </clothing>
 <clothing>
  <id>
   423833834
  </id>
  <name>
   PleinSport Handbags X-3852
  </name>
  <category>
   Handbags
  </category>
  <size>
   XL
  </size>
  <color>
   Голубой
  </color>
  <material>
   Вискоза
  </material>
  <price>
   656340
  </price>
  <rating>
   4.11
  </rating>
  <reviews>
   421336
  </reviews>
  <new>
   +
  </new>
  <sporty>
   no
  </sporty>
 </clothing>
 <clothing>
  <id>
   741249998
  </id>
  <name>
   Brooks Jeans Z-7742
  </name>
  <category>
   Jeans
  </category>
  <size>
   XXL
  </size>
  <color>
   Зеленый
  </color>
  <material>
   Хлопок
  </material>
  <price>
   626465
  </price>
  <rating>
   3.22
  </rating>
  <reviews>
   343229
  </reviews>
  <exclusive>
   yes
  </exclusive>
  <sporty>
   no
  </sporty>
 </clothing>
 <clothing>
  <id>
   242717793
  </id>
  <name>
   Fila Blouse V-3829
  </name>
  <category>
   Blouse
  </category>
  <size>
   L
  </size>
  <color>
   Желтый
  </color>
  <material>
   Полиэстер
  </material>
  <price>
   169488
  </price>
  <rating>
   4.69
  </rating>
  <reviews>
   813553
  </reviews>
  <new>
   -
  </new>
  <sporty>
   no
  </sporty>
 </clothing>
 <clothing>
  <id>
   874425375
  </id>
  <name>
   Nike Handbags T-9455
  </name>
  <category>
   Handbags
  </category>
  <size>
   XL
  </size>
  <color>
   Голубой
  </color>
  <material>
   Хлопок
  </material>
  <price>
   760570
  </price>
  <rating>
   3.15
  </rating>
  <reviews>
   589591
  </reviews>
 </clothing>
 <clothing>
  <id>
   209207690
  </id>
  <name>
   DC Hat Y-9061
  </name>
  <category>
   Hat
  </category>
  <size>
   XXL
  </size>
  <color>
   Зеленый
  </color>
  <material>
   Шерсть
  </material>
  <price>
   651429
  </price>
  <rating>
   4.7
  </rating>
  <reviews>
   678030
  </reviews>
  <new>
   -
  </new>
  <exclusive>
   yes
  </exclusive>
 </clothing>
 <clothing>
  <id>
   838986691
  </id>
  <name>
   New Balance Skirt K-1240
  </name>
  <category>
   Skirt
  </category>
  <size>
   S
  </size>
  <color>
   Зеленый
  </color>
  <material>
   Лен
  </material>
  <price>
   750733
  </price>
  <rating>
   2.42
  </rating>
  <reviews>
   459893
  </reviews>
  <new>
   +
  </new>
 </clothing>
 <clothing>
  <id>
   623939766
  </id>
  <name>
   Ellesse Sweater O-2930
  </name>
  <category>
   Sweater
  </category>
  <size>
   L
  </size>
  <color>
   Фиолетовый
  </color>
  <material>
   Кожа
  </material>
  <price>
   487337
  </price>
  <rating>
   4.97
  </rating>
  <reviews>
   37421
  </reviews>
  <new>
   +
  </new>
  <sporty>
   no
  </sporty>
 </clothing>
 <clothing>
  <id>
   584484977
  </id>
  <name>
   Puma Handbags R-2246
  </name>
  <category>
   Handbags
  </category>
  <size>
   XXL
  </size>
  <color>
   Голубой
  </color>
  <material>
   Лен
  </material>
  <price>
   139200
  </price>
  <rating>
   4.99
  </rating>
  <reviews>
   233542
  </reviews>
  <new>
   -
  </new>
  <exclusive>
   no
  </exclusive>
  <sporty>
   yes
  </sporty>
 </clothing>
 <clothing>
  <id>
   636192118
  </id>
  <name>
   Puma Sweater T-4691
  </name>
  <category>
   Sweater
  </category>
  <size>
   XL
  </size>
  <color>
   Зеленый
  </color>
  <material>
   Лен
  </material>
  <price>
   234570
  </price>
  <rating>
   4.24
  </rating>
  <reviews>
   869226
  </reviews>
  <new>
   -
  </new>
  <exclusive>
   yes
  </exclusive>
  <sporty>
   yes
  </sporty>
 </clothing>
 <clothing>
  <id>
   284114060
  </id>
  <name>
   Fila Shoes F-2119
  </name>
  <category>
   Shoes
  </category>
  <size>
   XL
  </size>
  <color>
   Синий
  </color>
  <material>
   Шерсть
  </material>
  <price>
   625140
  </price>
  <rating>
   1.35
  </rating>
  <reviews>
   174676
  </reviews>
  <exclusive>
   no
  </exclusive>
  <sporty>
   no
  </sporty>
 </clothing>
 <clothing>
  <id>
   943326862
  </id>
  <name>
   DC Sweater M-1988
  </name>
  <category>
   Sweater
  </category>
  <size>
   XL
  </size>
  <color>
   Голубой
  </color>
  <material>
   Кожа
  </material>
  <price>
   298711
  </price>
  <rating>
   1.1
  </rating>
  <reviews>
   449405
  </reviews>
  <sporty>
   no
  </sporty>
 </clothing>
 <clothing>
  <id>
   987506754
  </id>
  <name>
   Ellesse Umbrellas Q-2419
  </name>
  <category>
   Umbrellas
  </category>
  <size>
   M
  </size>
  <color>
   Оранжевый
  </color>
  <material>
   Шерсть
  </material>
  <price>
   347800
  </price>
  <rating>
   1.99
  </rating>
  <reviews>
   705729
  </reviews>
  <new>
   +
  </new>
  <exclusive>
   yes
  </exclusive>
  <sporty>
   no
  </sporty>
 </clothing>
 <clothing>
  <id>
   219759197
  </id>
  <name>
   PleinSport Skirt L-4098
  </name>
  <category>
   Skirt
  </category>
  <size>
   S
  </size>
  <color>
   Зеленый
  </color>
  <material>
   Вискоза
  </material>
  <price>
   195482
  </price>
  <rating>
   2.93
  </rating>
  <reviews>
   218923
  </reviews>
  <new>
   -
  </new>
  <exclusive>
   no
  </exclusive>
  <sporty>
   yes
  </sporty>
 </clothing>
 <clothing>
  <id>
   471337923
  </id>
  <name>
   Puma Jeans Y-2159
  </name>
  <category>
   Jeans
  </category>
  <size>
   XXL
  </size>
  <color>
   Голубой
  </color>
  <material>
   Хлопок
  </material>
  <price>
   720962
  </price>
  <rating>
   2.87
  </rating>
  <reviews>
   964161
  </reviews>
  <new>
   +
  </new>
  <exclusive>
   no
  </exclusive>
  <sporty>
   no
  </sporty>
 </clothing>
 <clothing>
  <id>
   929906309
  </id>
  <name>
   Asics Gloves I-4555
  </name>
  <category>
   Gloves
  </category>
  <size>
   XXL
  </size>
  <color>
   Фиолетовый
  </color>
  <material>
   Хлопок
  </material>
  <price>
   708425
  </price>
  <rating>
   1.13
  </rating>
  <reviews>
   245814
  </reviews>
  <exclusive>
   yes
  </exclusive>
  <sporty>
   no
  </sporty>
 </clothing>
 <clothing>
  <id>
   675549409
  </id>
  <name>
   New Balance Umbrellas Y-1328
  </name>
  <category>
   Umbrellas
  </category>
  <size>
   M
  </size>
  <color>
   Красный
  </color>
  <material>
   Шелк
  </material>
  <price>
   624424
  </price>
  <rating>
   2.25
  </rating>
  <reviews>
   406275
  </reviews>
  <new>
   +
  </new>
  <sporty>
   no
  </sporty>
 </clothing>
 <clothing>
  <id>
   688690361
  </id>
  <name>
   Adidas Pants R-5890
  </name>
  <category>
   Pants
  </category>
  <size>
   S
  </size>
  <color>
   Фиолетовый
  </color>
  <material>
   Нейлон
  </material>
  <price>
   904013
  </price>
  <rating>
   3.79
  </rating>
  <reviews>
   852065
  </reviews>
  <new>
   -
  </new>
  <exclusive>
   no
  </exclusive>
  <sporty>
   no
  </sporty>
 </clothing>
 <clothing>
  <id>
   320089790
  </id>
  <name>
   Puma Skirt T-9831
  </name>
  <category>
   Skirt
  </category>
  <size>
   M
  </size>
  <color>
   Желтый
  </color>
  <material>
   Шерсть
  </material>
  <price>
   916697
  </price>
  <rating>
   2.82
  </rating>
  <reviews>
   476982
  </reviews>
  <exclusive>
   yes
  </exclusive>
  <sporty>
   yes
  </sporty>
 </clothing>
 <clothing>
  <id>
   679263665
  </id>
  <name>
   Nike Gloves T-9154
  </name>
  <category>
   Gloves
  </category>
  <size>
   L
  </size>
  <color>
   Синий
  </color>
  <material>
   Нейлон
  </material>
  <price>
   321791
  </price>
  <rating>
   2.11
  </rating>
  <reviews>
   468820
  </reviews>
  <new>
   +
  </new>
  <exclusive>
   yes
  </exclusive>
 </clothing>
 <clothing>
  <id>
   996841450
  </id>
  <name>
   Reebok Skirt U-8390
  </name>
  <category>
   Skirt
  </category>
  <size>
   L
  </size>
  <color>
   Оранжевый
  </color>
  <material>
   Шерсть
  </material>
  <price>
   308100
  </price>
  <rating>
   1.43
  </rating>
  <reviews>
   259201
  </reviews>
  <new>
   +
  </new>
  <exclusive>
   no
  </exclusive>
  <sporty>
   yes
  </sporty>
 </clothing>
 <clothing>
  <id>
   487988974
  </id>
  <name>
   Lacoste Jeans M-5162
  </name>
  <category>
   Jeans
  </category>
  <size>
   XXL
  </size>
  <color>
   Фиолетовый
  </color>
  <material>
   Нейлон
  </material>
  <price>
   608349
  </price>
  <rating>
   4.31
  </rating>
  <reviews>
   527561
  </reviews>
  <new>
   +
  </new>
 </clothing>
 <clothing>
  <id>
   855291754
  </id>
  <name>
   PleinSport Gloves F-2855
  </name>
  <category>
   Gloves
  </category>
  <size>
   M
  </size>
  <color>
   Зеленый
  </color>
  <material>
   Полиэстер
  </material>
  <price>
   415994
  </price>
  <rating>
   1.17
  </rating>
  <reviews>
   430589
  </reviews>
  <new>
   -
  </new>
 </clothing>
 <clothing>
  <id>
   706648700
  </id>
  <name>
   Lacoste Jacket R-5056
  </name>
  <category>
   Jacket
  </category>
  <size>
   L
  </size>
  <color>
   Оранжевый
  </color>
  <material>
   Лен
  </material>
  <price>
   467205
  </price>
  <rating>
   1.39
  </rating>
  <reviews>
   952560
  </reviews>
  <exclusive>
   no
  </exclusive>
 </clothing>
 <clothing>
  <id>
   791656410
  </id>
  <name>
   Adidas Pants I-7212
  </name>
  <category>
   Pants
  </category>
  <size>
   S
  </size>
  <color>
   Желтый
  </color>
  <material>
   Нейлон
  </material>
  <price>
   624626
  </price>
  <rating>
   4.93
  </rating>
  <reviews>
   997931
  </reviews>
  <exclusive>
   yes
  </exclusive>
 </clothing>
</clothing-items>
