<?xml version="1.0" encoding="utf-8"?>
<clothing-items>
 <clothing>
  <id>
   440740381
  </id>
  <name>
   Addidas Handbags R-7088
  </name>
  <category>
   Handbags
  </category>
  <size>
   S
  </size>
  <color>
   Красный
  </color>
  <material>
   Полиэстер
  </material>
  <price>
   603621
  </price>
  <rating>
   1.14
  </rating>
  <reviews>
   311912
  </reviews>
  <new>
   -
  </new>
  <exclusive>
   yes
  </exclusive>
 </clothing>
 <clothing>
  <id>
   767731406
  </id>
  <name>
   Asics Hat U-8826
  </name>
  <category>
   Hat
  </category>
  <size>
   S
  </size>
  <color>
   Оранжевый
  </color>
  <material>
   Нейлон
  </material>
  <price>
   648971
  </price>
  <rating>
   2.18
  </rating>
  <reviews>
   308457
  </reviews>
  <new>
   +
  </new>
  <exclusive>
   yes
  </exclusive>
  <sporty>
   no
  </sporty>
 </clothing>
 <clothing>
  <id>
   797208987
  </id>
  <name>
   Lacoste Blouse Q-4250
  </name>
  <category>
   Blouse
  </category>
  <size>
   XXL
  </size>
  <color>
   Оранжевый
  </color>
  <material>
   Вискоза
  </material>
  <price>
   506654
  </price>
  <rating>
   3.88
  </rating>
  <reviews>
   578758
  </reviews>
  <new>
   -
  </new>
  <exclusive>
   no
  </exclusive>
 </clothing>
 <clothing>
  <id>
   654922302
  </id>
  <name>
   Adidas Jeans T-4696
  </name>
  <category>
   Jeans
  </category>
  <size>
   S
  </size>
  <color>
   Фиолетовый
  </color>
  <material>
   Нейлон
  </material>
  <price>
   189329
  </price>
  <rating>
   2.18
  </rating>
  <reviews>
   191340
  </reviews>
  <exclusive>
   no
  </exclusive>
  <sporty>
   no
  </sporty>
 </clothing>
 <clothing>
  <id>
   857143940
  </id>
  <name>
   Lacoste Sweater H-9007
  </name>
  <category>
   Sweater
  </category>
  <size>
   XXL
  </size>
  <color>
   Голубой
  </color>
  <material>
   Шерсть
  </material>
  <price>
   343583
  </price>
  <rating>
   1.78
  </rating>
  <reviews>
   131737
  </reviews>
  <exclusive>
   no
  </exclusive>
  <sporty>
   yes
  </sporty>
 </clothing>
 <clothing>
  <id>
   247296306
  </id>
  <name>
   Nike Skirt Q-9607
  </name>
  <category>
   Skirt
  </category>
  <size>
   S
  </size>
  <color>
   Голубой
  </color>
  <material>
   Шерсть
  </material>
  <price>
   637230
  </price>
  <rating>
   1.17
  </rating>
  <reviews>
   258666
  </reviews>
  <new>
   -
  </new>
 </clothing>
 <clothing>
  <id>
   685014755
  </id>
  <name>
   New Balance Umbrellas W-9112
  </name>
  <category>
   Umbrellas
  </category>
  <size>
   L
  </size>
  <color>
   Фиолетовый
  </color>
  <material>
   Шелк
  </material>
  <price>
   228509
  </price>
  <rating>
   3.1
  </rating>
  <reviews>
   892400
  </reviews>
  <exclusive>
   yes
  </exclusive>
  <sporty>
   no
  </sporty>
 </clothing>
 <clothing>
  <id>
   953134015
  </id>
  <name>
   New Balance Hat L-6290
  </name>
  <category>
   Hat
  </category>
  <size>
   XXL
  </size>
  <color>
   Оранжевый
  </color>
  <material>
   Хлопок
  </material>
  <price>
   495152
  </price>
  <rating>
   1.16
  </rating>
  <reviews>
   630929
  </reviews>
  <new>
   -
  </new>
  <sporty>
   no
  </sporty>
 </clothing>
 <clothing>
  <id>
   600181632
  </id>
  <name>
   Reebok Jeans E-9649
  </name>
  <category>
   Jeans
  </category>
  <size>
   XL
  </size>
  <color>
   Зеленый
  </color>
  <material>
   Вискоза
  </material>
  <price>
   824596
  </price>
  <rating>
   2.09
  </rating>
  <reviews>
   367950
  </reviews>
  <new>
   -
  </new>
  <sporty>
   no
  </sporty>
 </clothing>
 <clothing>
  <id>
   382957614
  </id>
  <name>
   PleinSport Pants Y-7409
  </name>
  <category>
   Pants
  </category>
  <size>
   M
  </size>
  <color>
   Оранжевый
  </color>
  <material>
   Нейлон
  </material>
  <price>
   942784
  </price>
  <rating>
   3.6
  </rating>
  <reviews>
   136746
  </reviews>
  <new>
   +
  </new>
  <sporty>
   no
  </sporty>
 </clothing>
</clothing-items>
