<?xml version="1.0" encoding="utf-8"?>
<clothing-items>
 <clothing>
  <id>
   462606205
  </id>
  <name>
   Brooks Gloves B-1268
  </name>
  <category>
   Gloves
  </category>
  <size>
   S
  </size>
  <color>
   Красный
  </color>
  <material>
   Полиэстер
  </material>
  <price>
   967439
  </price>
  <rating>
   4.46
  </rating>
  <reviews>
   865825
  </reviews>
  <exclusive>
   yes
  </exclusive>
 </clothing>
 <clothing>
  <id>
   695152147
  </id>
  <name>
   Addidas Dress X-1634
  </name>
  <category>
   Dress
  </category>
  <size>
   M
  </size>
  <color>
   Красный
  </color>
  <material>
   Хлопок
  </material>
  <price>
   968239
  </price>
  <rating>
   3.71
  </rating>
  <reviews>
   350550
  </reviews>
  <new>
   -
  </new>
  <exclusive>
   no
  </exclusive>
  <sporty>
   no
  </sporty>
 </clothing>
 <clothing>
  <id>
   175619781
  </id>
  <name>
   Reebok T-shirt J-2599
  </name>
  <category>
   T-shirt
  </category>
  <size>
   XL
  </size>
  <color>
   Голубой
  </color>
  <material>
   Вискоза
  </material>
  <price>
   845442
  </price>
  <rating>
   2.07
  </rating>
  <reviews>
   889494
  </reviews>
  <exclusive>
   yes
  </exclusive>
  <sporty>
   no
  </sporty>
 </clothing>
 <clothing>
  <id>
   115717205
  </id>
  <name>
   Nike Skirt O-5278
  </name>
  <category>
   Skirt
  </category>
  <size>
   XL
  </size>
  <color>
   Оранжевый
  </color>
  <material>
   Кожа
  </material>
  <price>
   785028
  </price>
  <rating>
   4.99
  </rating>
  <reviews>
   267857
  </reviews>
  <new>
   -
  </new>
 </clothing>
 <clothing>
  <id>
   256217825
  </id>
  <name>
   DC Blouse Z-2647
  </name>
  <category>
   Blouse
  </category>
  <size>
   XXL
  </size>
  <color>
   Синий
  </color>
  <material>
   Полиэстер
  </material>
  <price>
   254582
  </price>
  <rating>
   4.99
  </rating>
  <reviews>
   172793
  </reviews>
  <new>
   -
  </new>
  <exclusive>
   no
  </exclusive>
  <sporty>
   no
  </sporty>
 </clothing>
 <clothing>
  <id>
   585728060
  </id>
  <name>
   Nike T-shirt T-8348
  </name>
  <category>
   T-shirt
  </category>
  <size>
   XL
  </size>
  <color>
   Голубой
  </color>
  <material>
   Нейлон
  </material>
  <price>
   494449
  </price>
  <rating>
   4.53
  </rating>
  <reviews>
   963056
  </reviews>
  <exclusive>
   no
  </exclusive>
  <sporty>
   no
  </sporty>
 </clothing>
 <clothing>
  <id>
   950929351
  </id>
  <name>
   New Balance Hat L-3940
  </name>
  <category>
   Hat
  </category>
  <size>
   XXL
  </size>
  <color>
   Желтый
  </color>
  <material>
   Лен
  </material>
  <price>
   487198
  </price>
  <rating>
   4.76
  </rating>
  <reviews>
   417000
  </reviews>
  <sporty>
   no
  </sporty>
 </clothing>
 <clothing>
  <id>
   158787987
  </id>
  <name>
   New Balance Handbags X-4017
  </name>
  <category>
   Handbags
  </category>
  <size>
   XL
  </size>
  <color>
   Синий
  </color>
  <material>
   Шерсть
  </material>
  <price>
   476517
  </price>
  <rating>
   3.76
  </rating>
  <reviews>
   89105
  </reviews>
  <new>
   -
  </new>
  <exclusive>
   no
  </exclusive>
 </clothing>
 <clothing>
  <id>
   373865625
  </id>
  <name>
   Brooks Jeans T-7756
  </name>
  <category>
   Jeans
  </category>
  <size>
   XL
  </size>
  <color>
   Зеленый
  </color>
  <material>
   Кожа
  </material>
  <price>
   967277
  </price>
  <rating>
   1.41
  </rating>
  <reviews>
   69521
  </reviews>
  <new>
   +
  </new>
  <exclusive>
   yes
  </exclusive>
 </clothing>
 <clothing>
  <id>
   518082875
  </id>
  <name>
   Fila Handbags V-9996
  </name>
  <category>
   Handbags
  </category>
  <size>
   L
  </size>
  <color>
   Зеленый
  </color>
  <material>
   Полиэстер
  </material>
  <price>
   202768
  </price>
  <rating>
   1.44
  </rating>
  <reviews>
   185267
  </reviews>
 </clothing>
 <clothing>
  <id>
   138086982
  </id>
  <name>
   Addidas Shirt Z-9810
  </name>
  <category>
   Shirt
  </category>
  <size>
   M
  </size>
  <color>
   Оранжевый
  </color>
  <material>
   Хлопок
  </material>
  <price>
   111654
  </price>
  <rating>
   2.13
  </rating>
  <reviews>
   454057
  </reviews>
  <exclusive>
   yes
  </exclusive>
 </clothing>
 <clothing>
  <id>
   701619674
  </id>
  <name>
   DC Jeans D-4685
  </name>
  <category>
   Jeans
  </category>
  <size>
   XXL
  </size>
  <color>
   Желтый
  </color>
  <material>
   Шерсть
  </material>
  <price>
   425405
  </price>
  <rating>
   1.06
  </rating>
  <reviews>
   245124
  </reviews>
  <new>
   -
  </new>
 </clothing>
 <clothing>
  <id>
   574912257
  </id>
  <name>
   Ellesse Shoes H-7479
  </name>
  <category>
   Shoes
  </category>
  <size>
   S
  </size>
  <color>
   Красный
  </color>
  <material>
   Вискоза
  </material>
  <price>
   958196
  </price>
  <rating>
   3.81
  </rating>
  <reviews>
   122763
  </reviews>
  <sporty>
   yes
  </sporty>
 </clothing>
 <clothing>
  <id>
   496565596
  </id>
  <name>
   PleinSport Hat C-9024
  </name>
  <category>
   Hat
  </category>
  <size>
   XL
  </size>
  <color>
   Оранжевый
  </color>
  <material>
   Хлопок
  </material>
  <price>
   150276
  </price>
  <rating>
   2.01
  </rating>
  <reviews>
   88629
  </reviews>
  <exclusive>
   yes
  </exclusive>
 </clothing>
 <clothing>
  <id>
   476920894
  </id>
  <name>
   New Balance T-shirt K-5457
  </name>
  <category>
   T-shirt
  </category>
  <size>
   XL
  </size>
  <color>
   Зеленый
  </color>
  <material>
   Полиэстер
  </material>
  <price>
   514570
  </price>
  <rating>
   3.16
  </rating>
  <reviews>
   986991
  </reviews>
  <exclusive>
   no
  </exclusive>
  <sporty>
   yes
  </sporty>
 </clothing>
 <clothing>
  <id>
   147156000
  </id>
  <name>
   Lacoste Blouse N-3644
  </name>
  <category>
   Blouse
  </category>
  <size>
   M
  </size>
  <color>
   Желтый
  </color>
  <material>
   Шерсть
  </material>
  <price>
   667073
  </price>
  <rating>
   1.81
  </rating>
  <reviews>
   175183
  </reviews>
  <new>
   -
  </new>
  <exclusive>
   no
  </exclusive>
  <sporty>
   yes
  </sporty>
 </clothing>
 <clothing>
  <id>
   476807852
  </id>
  <name>
   Nike Hat L-7326
  </name>
  <category>
   Hat
  </category>
  <size>
   S
  </size>
  <color>
   Красный
  </color>
  <material>
   Кожа
  </material>
  <price>
   324289
  </price>
  <rating>
   4.98
  </rating>
  <reviews>
   836041
  </reviews>
  <exclusive>
   no
  </exclusive>
  <sporty>
   no
  </sporty>
 </clothing>
 <clothing>
  <id>
   796744845
  </id>
  <name>
   Fila Hat V-4224
  </name>
  <category>
   Hat
  </category>
  <size>
   XL
  </size>
  <color>
   Красный
  </color>
  <material>
   Шелк
  </material>
  <price>
   837598
  </price>
  <rating>
   4.85
  </rating>
  <reviews>
   509673
  </reviews>
  <new>
   +
  </new>
 </clothing>
 <clothing>
  <id>
   219425224
  </id>
  <name>
   New Balance Pants N-6826
  </name>
  <category>
   Pants
  </category>
  <size>
   L
  </size>
  <color>
   Красный
  </color>
  <material>
   Шелк
  </material>
  <price>
   375075
  </price>
  <rating>
   4.69
  </rating>
  <reviews>
   238993
  </reviews>
 </clothing>
 <clothing>
  <id>
   672520280
  </id>
  <name>
   Adidas Dress U-5100
  </name>
  <category>
   Dress
  </category>
  <size>
   XL
  </size>
  <color>
   Синий
  </color>
  <material>
   Шерсть
  </material>
  <price>
   721571
  </price>
  <rating>
   4.12
  </rating>
  <reviews>
   781069
  </reviews>
  <new>
   -
  </new>
  <exclusive>
   yes
  </exclusive>
 </clothing>
 <clothing>
  <id>
   588262126
  </id>
  <name>
   PleinSport Umbrellas H-4348
  </name>
  <category>
   Umbrellas
  </category>
  <size>
   M
  </size>
  <color>
   Синий
  </color>
  <material>
   Вискоза
  </material>
  <price>
   726736
  </price>
  <rating>
   4.89
  </rating>
  <reviews>
   951857
  </reviews>
  <new>
   +
  </new>
  <sporty>
   yes
  </sporty>
 </clothing>
 <clothing>
  <id>
   656049707
  </id>
  <name>
   Vans Socks D-7542
  </name>
  <category>
   Socks
  </category>
  <size>
   S
  </size>
  <color>
   Оранжевый
  </color>
  <material>
   Шерсть
  </material>
  <price>
   728584
  </price>
  <rating>
   1.88
  </rating>
  <reviews>
   670577
  </reviews>
  <sporty>
   no
  </sporty>
 </clothing>
 <clothing>
  <id>
   857076585
  </id>
  <name>
   DC Shirt Y-9893
  </name>
  <category>
   Shirt
  </category>
  <size>
   S
  </size>
  <color>
   Голубой
  </color>
  <material>
   Нейлон
  </material>
  <price>
   926459
  </price>
  <rating>
   1.28
  </rating>
  <reviews>
   812722
  </reviews>
  <new>
   +
  </new>
 </clothing>
 <clothing>
  <id>
   161123489
  </id>
  <name>
   Ellesse Blouse F-6648
  </name>
  <category>
   Blouse
  </category>
  <size>
   XXL
  </size>
  <color>
   Синий
  </color>
  <material>
   Нейлон
  </material>
  <price>
   568319
  </price>
  <rating>
   2.11
  </rating>
  <reviews>
   421808
  </reviews>
  <exclusive>
   yes
  </exclusive>
  <sporty>
   yes
  </sporty>
 </clothing>
 <clothing>
  <id>
   188948556
  </id>
  <name>
   Asics T-shirt D-3312
  </name>
  <category>
   T-shirt
  </category>
  <size>
   XL
  </size>
  <color>
   Синий
  </color>
  <material>
   Полиэстер
  </material>
  <price>
   561066
  </price>
  <rating>
   1.78
  </rating>
  <reviews>
   740361
  </reviews>
  <new>
   -
  </new>
  <exclusive>
   no
  </exclusive>
  <sporty>
   yes
  </sporty>
 </clothing>
 <clothing>
  <id>
   174067756
  </id>
  <name>
   Fila Hat Q-6011
  </name>
  <category>
   Hat
  </category>
  <size>
   XXL
  </size>
  <color>
   Зеленый
  </color>
  <material>
   Кожа
  </material>
  <price>
   185059
  </price>
  <rating>
   3.7
  </rating>
  <reviews>
   279724
  </reviews>
  <exclusive>
   yes
  </exclusive>
  <sporty>
   no
  </sporty>
 </clothing>
 <clothing>
  <id>
   667885586
  </id>
  <name>
   Lacoste Dress J-4064
  </name>
  <category>
   Dress
  </category>
  <size>
   M
  </size>
  <color>
   Голубой
  </color>
  <material>
   Нейлон
  </material>
  <price>
   951710
  </price>
  <rating>
   4.14
  </rating>
  <reviews>
   203983
  </reviews>
  <new>
   -
  </new>
  <sporty>
   no
  </sporty>
 </clothing>
 <clothing>
  <id>
   457945530
  </id>
  <name>
   Asics Socks A-3247
  </name>
  <category>
   Socks
  </category>
  <size>
   L
  </size>
  <color>
   Фиолетовый
  </color>
  <material>
   Полиэстер
  </material>
  <price>
   708334
  </price>
  <rating>
   4.7
  </rating>
  <reviews>
   17867
  </reviews>
  <new>
   -
  </new>
  <sporty>
   yes
  </sporty>
 </clothing>
 <clothing>
  <id>
   653514068
  </id>
  <name>
   Converse T-shirt H-2138
  </name>
  <category>
   T-shirt
  </category>
  <size>
   L
  </size>
  <color>
   Оранжевый
  </color>
  <material>
   Вискоза
  </material>
  <price>
   135958
  </price>
  <rating>
   2.93
  </rating>
  <reviews>
   179835
  </reviews>
  <new>
   -
  </new>
  <exclusive>
   no
  </exclusive>
 </clothing>
 <clothing>
  <id>
   233219985
  </id>
  <name>
   Vans Umbrellas L-7437
  </name>
  <category>
   Umbrellas
  </category>
  <size>
   S
  </size>
  <color>
   Зеленый
  </color>
  <material>
   Лен
  </material>
  <price>
   903737
  </price>
  <rating>
   1.91
  </rating>
  <reviews>
   449407
  </reviews>
  <sporty>
   no
  </sporty>
 </clothing>
 <clothing>
  <id>
   369734846
  </id>
  <name>
   Nike Dress P-5962
  </name>
  <category>
   Dress
  </category>
  <size>
   S
  </size>
  <color>
   Голубой
  </color>
  <material>
   Шелк
  </material>
  <price>
   233628
  </price>
  <rating>
   3.13
  </rating>
  <reviews>
   304627
  </reviews>
  <exclusive>
   no
  </exclusive>
 </clothing>
 <clothing>
  <id>
   348512177
  </id>
  <name>
   Brooks Belts Y-7420
  </name>
  <category>
   Belts
  </category>
  <size>
   XXL
  </size>
  <color>
   Фиолетовый
  </color>
  <material>
   Полиэстер
  </material>
  <price>
   375103
  </price>
  <rating>
   1.17
  </rating>
  <reviews>
   180589
  </reviews>
  <new>
   +
  </new>
  <exclusive>
   yes
  </exclusive>
  <sporty>
   yes
  </sporty>
 </clothing>
 <clothing>
  <id>
   903108473
  </id>
  <name>
   Puma Jeans S-8619
  </name>
  <category>
   Jeans
  </category>
  <size>
   M
  </size>
  <color>
   Оранжевый
  </color>
  <material>
   Лен
  </material>
  <price>
   595246
  </price>
  <rating>
   3.63
  </rating>
  <reviews>
   625705
  </reviews>
  <new>
   -
  </new>
 </clothing>
 <clothing>
  <id>
   112518240
  </id>
  <name>
   Ellesse Shoes I-8871
  </name>
  <category>
   Shoes
  </category>
  <size>
   XL
  </size>
  <color>
   Синий
  </color>
  <material>
   Шелк
  </material>
  <price>
   434412
  </price>
  <rating>
   2.25
  </rating>
  <reviews>
   574985
  </reviews>
  <new>
   +
  </new>
  <sporty>
   no
  </sporty>
 </clothing>
 <clothing>
  <id>
   167865048
  </id>
  <name>
   Adidas Blouse W-5974
  </name>
  <category>
   Blouse
  </category>
  <size>
   M
  </size>
  <color>
   Синий
  </color>
  <material>
   Шерсть
  </material>
  <price>
   593348
  </price>
  <rating>
   1.27
  </rating>
  <reviews>
   53003
  </reviews>
  <new>
   -
  </new>
 </clothing>
 <clothing>
  <id>
   179845117
  </id>
  <name>
   Brooks Umbrellas U-9749
  </name>
  <category>
   Umbrellas
  </category>
  <size>
   L
  </size>
  <color>
   Желтый
  </color>
  <material>
   Нейлон
  </material>
  <price>
   795109
  </price>
  <rating>
   2.19
  </rating>
  <reviews>
   810061
  </reviews>
  <new>
   +
  </new>
  <sporty>
   no
  </sporty>
 </clothing>
</clothing-items>
