<?xml version="1.0" encoding="utf-8"?>
<clothing-items>
 <clothing>
  <id>
   783423862
  </id>
  <name>
   Under Armour Pants H-5177
  </name>
  <category>
   Pants
  </category>
  <size>
   XL
  </size>
  <color>
   Синий
  </color>
  <material>
   Хлопок
  </material>
  <price>
   558992
  </price>
  <rating>
   1.88
  </rating>
  <reviews>
   199719
  </reviews>
  <exclusive>
   yes
  </exclusive>
  <sporty>
   yes
  </sporty>
 </clothing>
 <clothing>
  <id>
   504074259
  </id>
  <name>
   Adidas Shoes X-7912
  </name>
  <category>
   Shoes
  </category>
  <size>
   L
  </size>
  <color>
   Зеленый
  </color>
  <material>
   Полиэстер
  </material>
  <price>
   216987
  </price>
  <rating>
   2.21
  </rating>
  <reviews>
   955477
  </reviews>
  <new>
   -
  </new>
  <sporty>
   yes
  </sporty>
 </clothing>
 <clothing>
  <id>
   841966948
  </id>
  <name>
   Addidas Socks V-6020
  </name>
  <category>
   Socks
  </category>
  <size>
   XXL
  </size>
  <color>
   Красный
  </color>
  <material>
   Кожа
  </material>
  <price>
   606807
  </price>
  <rating>
   1.33
  </rating>
  <reviews>
   571757
  </reviews>
  <sporty>
   no
  </sporty>
 </clothing>
 <clothing>
  <id>
   566200480
  </id>
  <name>
   Addidas Socks R-8823
  </name>
  <category>
   Socks
  </category>
  <size>
   L
  </size>
  <color>
   Фиолетовый
  </color>
  <material>
   Шерсть
  </material>
  <price>
   703255
  </price>
  <rating>
   1.85
  </rating>
  <reviews>
   324316
  </reviews>
 </clothing>
 <clothing>
  <id>
   304730339
  </id>
  <name>
   Under Armour Dress Q-7131
  </name>
  <category>
   Dress
  </category>
  <size>
   M
  </size>
  <color>
   Синий
  </color>
  <material>
   Лен
  </material>
  <price>
   606159
  </price>
  <rating>
   4.75
  </rating>
  <reviews>
   267742
  </reviews>
  <new>
   +
  </new>
  <sporty>
   no
  </sporty>
 </clothing>
 <clothing>
  <id>
   577860093
  </id>
  <name>
   Under Armour Skirt V-3165
  </name>
  <category>
   Skirt
  </category>
  <size>
   XXL
  </size>
  <color>
   Фиолетовый
  </color>
  <material>
   Шерсть
  </material>
  <price>
   197983
  </price>
  <rating>
   4.31
  </rating>
  <reviews>
   527077
  </reviews>
  <new>
   +
  </new>
  <exclusive>
   no
  </exclusive>
  <sporty>
   no
  </sporty>
 </clothing>
 <clothing>
  <id>
   381391397
  </id>
  <name>
   DC Skirt D-5868
  </name>
  <category>
   Skirt
  </category>
  <size>
   XL
  </size>
  <color>
   Голубой
  </color>
  <material>
   Лен
  </material>
  <price>
   623614
  </price>
  <rating>
   3.83
  </rating>
  <reviews>
   110786
  </reviews>
  <exclusive>
   no
  </exclusive>
  <sporty>
   yes
  </sporty>
 </clothing>
 <clothing>
  <id>
   773269962
  </id>
  <name>
   Vans Skirt Z-5651
  </name>
  <category>
   Skirt
  </category>
  <size>
   XL
  </size>
  <color>
   Красный
  </color>
  <material>
   Шелк
  </material>
  <price>
   860088
  </price>
  <rating>
   4.54
  </rating>
  <reviews>
   43304
  </reviews>
 </clothing>
 <clothing>
  <id>
   214492622
  </id>
  <name>
   Puma Umbrellas E-7979
  </name>
  <category>
   Umbrellas
  </category>
  <size>
   XXL
  </size>
  <color>
   Голубой
  </color>
  <material>
   Нейлон
  </material>
  <price>
   154236
  </price>
  <rating>
   1.1
  </rating>
  <reviews>
   524938
  </reviews>
  <new>
   -
  </new>
  <exclusive>
   no
  </exclusive>
 </clothing>
 <clothing>
  <id>
   365588567
  </id>
  <name>
   DC Hat K-5504
  </name>
  <category>
   Hat
  </category>
  <size>
   L
  </size>
  <color>
   Фиолетовый
  </color>
  <material>
   Кожа
  </material>
  <price>
   935360
  </price>
  <rating>
   4.15
  </rating>
  <reviews>
   623143
  </reviews>
  <new>
   -
  </new>
  <exclusive>
   yes
  </exclusive>
  <sporty>
   yes
  </sporty>
 </clothing>
 <clothing>
  <id>
   751504479
  </id>
  <name>
   Ellesse Shoes D-5162
  </name>
  <category>
   Shoes
  </category>
  <size>
   XL
  </size>
  <color>
   Желтый
  </color>
  <material>
   Нейлон
  </material>
  <price>
   282007
  </price>
  <rating>
   2.85
  </rating>
  <reviews>
   319752
  </reviews>
  <new>
   +
  </new>
  <sporty>
   yes
  </sporty>
 </clothing>
 <clothing>
  <id>
   435356638
  </id>
  <name>
   Ellesse Sweater R-9420
  </name>
  <category>
   Sweater
  </category>
  <size>
   S
  </size>
  <color>
   Оранжевый
  </color>
  <material>
   Нейлон
  </material>
  <price>
   532577
  </price>
  <rating>
   2.19
  </rating>
  <reviews>
   492439
  </reviews>
  <exclusive>
   no
  </exclusive>
 </clothing>
 <clothing>
  <id>
   860190641
  </id>
  <name>
   Lacoste Blouse N-3353
  </name>
  <category>
   Blouse
  </category>
  <size>
   XXL
  </size>
  <color>
   Голубой
  </color>
  <material>
   Полиэстер
  </material>
  <price>
   587564
  </price>
  <rating>
   4.8
  </rating>
  <reviews>
   886354
  </reviews>
  <new>
   -
  </new>
  <sporty>
   yes
  </sporty>
 </clothing>
 <clothing>
  <id>
   560564914
  </id>
  <name>
   Adidas Pants Z-5625
  </name>
  <category>
   Pants
  </category>
  <size>
   L
  </size>
  <color>
   Синий
  </color>
  <material>
   Полиэстер
  </material>
  <price>
   594121
  </price>
  <rating>
   4.3
  </rating>
  <reviews>
   927488
  </reviews>
  <new>
   +
  </new>
  <sporty>
   no
  </sporty>
 </clothing>
 <clothing>
  <id>
   206860866
  </id>
  <name>
   DC Jacket Z-9631
  </name>
  <category>
   Jacket
  </category>
  <size>
   S
  </size>
  <color>
   Красный
  </color>
  <material>
   Вискоза
  </material>
  <price>
   584477
  </price>
  <rating>
   4.45
  </rating>
  <reviews>
   271922
  </reviews>
  <exclusive>
   no
  </exclusive>
  <sporty>
   no
  </sporty>
 </clothing>
 <clothing>
  <id>
   459761913
  </id>
  <name>
   PleinSport Socks S-7048
  </name>
  <category>
   Socks
  </category>
  <size>
   M
  </size>
  <color>
   Синий
  </color>
  <material>
   Нейлон
  </material>
  <price>
   655873
  </price>
  <rating>
   1.61
  </rating>
  <reviews>
   455839
  </reviews>
  <new>
   -
  </new>
  <exclusive>
   yes
  </exclusive>
 </clothing>
 <clothing>
  <id>
   706536986
  </id>
  <name>
   Fila Handbags A-1700
  </name>
  <category>
   Handbags
  </category>
  <size>
   XL
  </size>
  <color>
   Красный
  </color>
  <material>
   Шерсть
  </material>
  <price>
   817599
  </price>
  <rating>
   1.34
  </rating>
  <reviews>
   84234
  </reviews>
  <new>
   -
  </new>
  <sporty>
   no
  </sporty>
 </clothing>
</clothing-items>
