<?xml version="1.0" encoding="utf-8"?>
<clothing-items>
 <clothing>
  <id>
   601295778
  </id>
  <name>
   Brooks Socks G-7026
  </name>
  <category>
   Socks
  </category>
  <size>
   L
  </size>
  <color>
   Красный
  </color>
  <material>
   Вискоза
  </material>
  <price>
   579410
  </price>
  <rating>
   4.06
  </rating>
  <reviews>
   830808
  </reviews>
 </clothing>
 <clothing>
  <id>
   411719071
  </id>
  <name>
   Reebok Socks R-4332
  </name>
  <category>
   Socks
  </category>
  <size>
   L
  </size>
  <color>
   Красный
  </color>
  <material>
   Шелк
  </material>
  <price>
   558621
  </price>
  <rating>
   2.08
  </rating>
  <reviews>
   480638
  </reviews>
  <new>
   -
  </new>
  <exclusive>
   no
  </exclusive>
  <sporty>
   yes
  </sporty>
 </clothing>
 <clothing>
  <id>
   226115030
  </id>
  <name>
   Ellesse Gloves Z-9258
  </name>
  <category>
   Gloves
  </category>
  <size>
   S
  </size>
  <color>
   Зеленый
  </color>
  <material>
   Шерсть
  </material>
  <price>
   362417
  </price>
  <rating>
   3.75
  </rating>
  <reviews>
   91865
  </reviews>
  <exclusive>
   yes
  </exclusive>
 </clothing>
 <clothing>
  <id>
   356385235
  </id>
  <name>
   Brooks Hat M-4929
  </name>
  <category>
   Hat
  </category>
  <size>
   XL
  </size>
  <color>
   Синий
  </color>
  <material>
   Хлопок
  </material>
  <price>
   786662
  </price>
  <rating>
   3.08
  </rating>
  <reviews>
   474361
  </reviews>
  <new>
   +
  </new>
  <exclusive>
   yes
  </exclusive>
  <sporty>
   no
  </sporty>
 </clothing>
 <clothing>
  <id>
   950930978
  </id>
  <name>
   Under Armour Belts X-7719
  </name>
  <category>
   Belts
  </category>
  <size>
   XXL
  </size>
  <color>
   Фиолетовый
  </color>
  <material>
   Нейлон
  </material>
  <price>
   371632
  </price>
  <rating>
   4.86
  </rating>
  <reviews>
   184584
  </reviews>
  <new>
   -
  </new>
  <exclusive>
   no
  </exclusive>
 </clothing>
 <clothing>
  <id>
   165934349
  </id>
  <name>
   Puma Sweater B-2394
  </name>
  <category>
   Sweater
  </category>
  <size>
   XXL
  </size>
  <color>
   Желтый
  </color>
  <material>
   Лен
  </material>
  <price>
   384941
  </price>
  <rating>
   1.55
  </rating>
  <reviews>
   231885
  </reviews>
  <new>
   -
  </new>
  <sporty>
   yes
  </sporty>
 </clothing>
 <clothing>
  <id>
   898557986
  </id>
  <name>
   Brooks Socks P-5901
  </name>
  <category>
   Socks
  </category>
  <size>
   S
  </size>
  <color>
   Голубой
  </color>
  <material>
   Хлопок
  </material>
  <price>
   133247
  </price>
  <rating>
   2.35
  </rating>
  <reviews>
   9468
  </reviews>
  <exclusive>
   no
  </exclusive>
 </clothing>
 <clothing>
  <id>
   479730591
  </id>
  <name>
   DC Handbags U-6336
  </name>
  <category>
   Handbags
  </category>
  <size>
   S
  </size>
  <color>
   Желтый
  </color>
  <material>
   Кожа
  </material>
  <price>
   894205
  </price>
  <rating>
   3.23
  </rating>
  <reviews>
   499012
  </reviews>
  <exclusive>
   no
  </exclusive>
  <sporty>
   yes
  </sporty>
 </clothing>
 <clothing>
  <id>
   217044002
  </id>
  <name>
   DC Belts W-7407
  </name>
  <category>
   Belts
  </category>
  <size>
   XL
  </size>
  <color>
   Синий
  </color>
  <material>
   Лен
  </material>
  <price>
   287364
  </price>
  <rating>
   4.53
  </rating>
  <reviews>
   733904
  </reviews>
  <new>
   -
  </new>
 </clothing>
 <clothing>
  <id>
   495127779
  </id>
  <name>
   Converse Sweater E-1457
  </name>
  <category>
   Sweater
  </category>
  <size>
   XXL
  </size>
  <color>
   Желтый
  </color>
  <material>
   Шелк
  </material>
  <price>
   198466
  </price>
  <rating>
   2.35
  </rating>
  <reviews>
   692258
  </reviews>
  <sporty>
   yes
  </sporty>
 </clothing>
 <clothing>
  <id>
   225221642
  </id>
  <name>
   Converse Sweater Z-7901
  </name>
  <category>
   Sweater
  </category>
  <size>
   L
  </size>
  <color>
   Желтый
  </color>
  <material>
   Шерсть
  </material>
  <price>
   403655
  </price>
  <rating>
   3.74
  </rating>
  <reviews>
   128880
  </reviews>
  <new>
   -
  </new>
  <sporty>
   no
  </sporty>
 </clothing>
 <clothing>
  <id>
   150236697
  </id>
  <name>
   Reebok Dress C-2646
  </name>
  <category>
   Dress
  </category>
  <size>
   XXL
  </size>
  <color>
   Фиолетовый
  </color>
  <material>
   Нейлон
  </material>
  <price>
   795572
  </price>
  <rating>
   3.49
  </rating>
  <reviews>
   886047
  </reviews>
  <exclusive>
   yes
  </exclusive>
 </clothing>
 <clothing>
  <id>
   121342348
  </id>
  <name>
   PleinSport Dress D-2467
  </name>
  <category>
   Dress
  </category>
  <size>
   L
  </size>
  <color>
   Желтый
  </color>
  <material>
   Нейлон
  </material>
  <price>
   499930
  </price>
  <rating>
   3.93
  </rating>
  <reviews>
   12183
  </reviews>
 </clothing>
 <clothing>
  <id>
   321971449
  </id>
  <name>
   Addidas Skirt S-4734
  </name>
  <category>
   Skirt
  </category>
  <size>
   L
  </size>
  <color>
   Голубой
  </color>
  <material>
   Вискоза
  </material>
  <price>
   154790
  </price>
  <rating>
   3.46
  </rating>
  <reviews>
   909301
  </reviews>
  <exclusive>
   no
  </exclusive>
 </clothing>
 <clothing>
  <id>
   972404717
  </id>
  <name>
   Asics Skirt B-2493
  </name>
  <category>
   Skirt
  </category>
  <size>
   M
  </size>
  <color>
   Красный
  </color>
  <material>
   Шелк
  </material>
  <price>
   942001
  </price>
  <rating>
   1.7
  </rating>
  <reviews>
   997347
  </reviews>
  <exclusive>
   yes
  </exclusive>
 </clothing>
 <clothing>
  <id>
   102607001
  </id>
  <name>
   Adidas Jacket J-7415
  </name>
  <category>
   Jacket
  </category>
  <size>
   XL
  </size>
  <color>
   Зеленый
  </color>
  <material>
   Лен
  </material>
  <price>
   384585
  </price>
  <rating>
   3.35
  </rating>
  <reviews>
   663981
  </reviews>
 </clothing>
 <clothing>
  <id>
   577695009
  </id>
  <name>
   Adidas Socks D-4378
  </name>
  <category>
   Socks
  </category>
  <size>
   S
  </size>
  <color>
   Желтый
  </color>
  <material>
   Полиэстер
  </material>
  <price>
   361211
  </price>
  <rating>
   3.72
  </rating>
  <reviews>
   471698
  </reviews>
  <new>
   -
  </new>
  <exclusive>
   no
  </exclusive>
  <sporty>
   yes
  </sporty>
 </clothing>
 <clothing>
  <id>
   887912831
  </id>
  <name>
   Addidas Sweater D-6638
  </name>
  <category>
   Sweater
  </category>
  <size>
   S
  </size>
  <color>
   Синий
  </color>
  <material>
   Шерсть
  </material>
  <price>
   979091
  </price>
  <rating>
   4.59
  </rating>
  <reviews>
   293621
  </reviews>
  <exclusive>
   no
  </exclusive>
 </clothing>
 <clothing>
  <id>
   674973172
  </id>
  <name>
   Lacoste Jacket S-8005
  </name>
  <category>
   Jacket
  </category>
  <size>
   M
  </size>
  <color>
   Оранжевый
  </color>
  <material>
   Нейлон
  </material>
  <price>
   393573
  </price>
  <rating>
   2.47
  </rating>
  <reviews>
   971882
  </reviews>
  <new>
   +
  </new>
  <sporty>
   no
  </sporty>
 </clothing>
 <clothing>
  <id>
   501500403
  </id>
  <name>
   Addidas T-shirt X-8639
  </name>
  <category>
   T-shirt
  </category>
  <size>
   M
  </size>
  <color>
   Синий
  </color>
  <material>
   Шерсть
  </material>
  <price>
   880864
  </price>
  <rating>
   1.36
  </rating>
  <reviews>
   171632
  </reviews>
  <new>
   -
  </new>
 </clothing>
 <clothing>
  <id>
   461871999
  </id>
  <name>
   DC Gloves I-4014
  </name>
  <category>
   Gloves
  </category>
  <size>
   M
  </size>
  <color>
   Фиолетовый
  </color>
  <material>
   Шерсть
  </material>
  <price>
   667408
  </price>
  <rating>
   2.65
  </rating>
  <reviews>
   587316
  </reviews>
  <exclusive>
   yes
  </exclusive>
  <sporty>
   no
  </sporty>
 </clothing>
 <clothing>
  <id>
   839400307
  </id>
  <name>
   Addidas Shirt A-7058
  </name>
  <category>
   Shirt
  </category>
  <size>
   L
  </size>
  <color>
   Голубой
  </color>
  <material>
   Кожа
  </material>
  <price>
   371100
  </price>
  <rating>
   4.5
  </rating>
  <reviews>
   533120
  </reviews>
  <new>
   +
  </new>
  <sporty>
   yes
  </sporty>
 </clothing>
 <clothing>
  <id>
   229456743
  </id>
  <name>
   PleinSport Blouse U-9904
  </name>
  <category>
   Blouse
  </category>
  <size>
   XL
  </size>
  <color>
   Красный
  </color>
  <material>
   Полиэстер
  </material>
  <price>
   528764
  </price>
  <rating>
   2.77
  </rating>
  <reviews>
   498206
  </reviews>
 </clothing>
</clothing-items>
