<?xml version="1.0" encoding="utf-8"?>
<clothing-items>
 <clothing>
  <id>
   656457810
  </id>
  <name>
   Under Armour Belts P-7489
  </name>
  <category>
   Belts
  </category>
  <size>
   XL
  </size>
  <color>
   Зеленый
  </color>
  <material>
   Шерсть
  </material>
  <price>
   585401
  </price>
  <rating>
   3.12
  </rating>
  <reviews>
   793453
  </reviews>
  <new>
   -
  </new>
  <sporty>
   no
  </sporty>
 </clothing>
 <clothing>
  <id>
   852188722
  </id>
  <name>
   Asics Dress S-7519
  </name>
  <category>
   Dress
  </category>
  <size>
   XL
  </size>
  <color>
   Голубой
  </color>
  <material>
   Лен
  </material>
  <price>
   929431
  </price>
  <rating>
   3.66
  </rating>
  <reviews>
   333927
  </reviews>
  <exclusive>
   yes
  </exclusive>
  <sporty>
   no
  </sporty>
 </clothing>
 <clothing>
  <id>
   494577296
  </id>
  <name>
   PleinSport Jacket J-5443
  </name>
  <category>
   Jacket
  </category>
  <size>
   M
  </size>
  <color>
   Желтый
  </color>
  <material>
   Нейлон
  </material>
  <price>
   954360
  </price>
  <rating>
   4.76
  </rating>
  <reviews>
   804617
  </reviews>
  <new>
   +
  </new>
  <sporty>
   no
  </sporty>
 </clothing>
 <clothing>
  <id>
   320113463
  </id>
  <name>
   Brooks Sweater V-9546
  </name>
  <category>
   Sweater
  </category>
  <size>
   M
  </size>
  <color>
   Желтый
  </color>
  <material>
   Шерсть
  </material>
  <price>
   404742
  </price>
  <rating>
   4.16
  </rating>
  <reviews>
   703923
  </reviews>
  <exclusive>
   yes
  </exclusive>
 </clothing>
 <clothing>
  <id>
   449503326
  </id>
  <name>
   Lacoste Shoes T-7052
  </name>
  <category>
   Shoes
  </category>
  <size>
   M
  </size>
  <color>
   Голубой
  </color>
  <material>
   Шерсть
  </material>
  <price>
   671634
  </price>
  <rating>
   4.73
  </rating>
  <reviews>
   849783
  </reviews>
  <new>
   +
  </new>
 </clothing>
 <clothing>
  <id>
   107076256
  </id>
  <name>
   Under Armour T-shirt J-7793
  </name>
  <category>
   T-shirt
  </category>
  <size>
   XXL
  </size>
  <color>
   Красный
  </color>
  <material>
   Хлопок
  </material>
  <price>
   235252
  </price>
  <rating>
   2.71
  </rating>
  <reviews>
   20893
  </reviews>
  <new>
   -
  </new>
  <sporty>
   no
  </sporty>
 </clothing>
 <clothing>
  <id>
   396145075
  </id>
  <name>
   DC Pants B-8010
  </name>
  <category>
   Pants
  </category>
  <size>
   M
  </size>
  <color>
   Голубой
  </color>
  <material>
   Шелк
  </material>
  <price>
   710398
  </price>
  <rating>
   4.71
  </rating>
  <reviews>
   995013
  </reviews>
  <sporty>
   no
  </sporty>
 </clothing>
 <clothing>
  <id>
   317298670
  </id>
  <name>
   New Balance Umbrellas J-7598
  </name>
  <category>
   Umbrellas
  </category>
  <size>
   L
  </size>
  <color>
   Желтый
  </color>
  <material>
   Шерсть
  </material>
  <price>
   839694
  </price>
  <rating>
   2.01
  </rating>
  <reviews>
   474892
  </reviews>
  <new>
   +
  </new>
  <exclusive>
   no
  </exclusive>
 </clothing>
 <clothing>
  <id>
   316051962
  </id>
  <name>
   Ellesse Belts L-7629
  </name>
  <category>
   Belts
  </category>
  <size>
   L
  </size>
  <color>
   Синий
  </color>
  <material>
   Лен
  </material>
  <price>
   940584
  </price>
  <rating>
   4.93
  </rating>
  <reviews>
   803466
  </reviews>
  <new>
   -
  </new>
  <exclusive>
   no
  </exclusive>
  <sporty>
   no
  </sporty>
 </clothing>
 <clothing>
  <id>
   363682291
  </id>
  <name>
   Asics Belts D-6646
  </name>
  <category>
   Belts
  </category>
  <size>
   M
  </size>
  <color>
   Голубой
  </color>
  <material>
   Лен
  </material>
  <price>
   956204
  </price>
  <rating>
   4.4
  </rating>
  <reviews>
   279360
  </reviews>
  <exclusive>
   no
  </exclusive>
 </clothing>
 <clothing>
  <id>
   695310034
  </id>
  <name>
   Ellesse Jacket K-1065
  </name>
  <category>
   Jacket
  </category>
  <size>
   S
  </size>
  <color>
   Голубой
  </color>
  <material>
   Хлопок
  </material>
  <price>
   957800
  </price>
  <rating>
   4.44
  </rating>
  <reviews>
   956283
  </reviews>
  <new>
   -
  </new>
  <exclusive>
   yes
  </exclusive>
 </clothing>
 <clothing>
  <id>
   431402019
  </id>
  <name>
   New Balance Shirt Q-4980
  </name>
  <category>
   Shirt
  </category>
  <size>
   S
  </size>
  <color>
   Фиолетовый
  </color>
  <material>
   Хлопок
  </material>
  <price>
   760660
  </price>
  <rating>
   4.33
  </rating>
  <reviews>
   579353
  </reviews>
  <sporty>
   no
  </sporty>
 </clothing>
 <clothing>
  <id>
   139120421
  </id>
  <name>
   Asics Jacket A-8274
  </name>
  <category>
   Jacket
  </category>
  <size>
   S
  </size>
  <color>
   Зеленый
  </color>
  <material>
   Нейлон
  </material>
  <price>
   741492
  </price>
  <rating>
   3.27
  </rating>
  <reviews>
   904444
  </reviews>
  <new>
   -
  </new>
 </clothing>
 <clothing>
  <id>
   452434015
  </id>
  <name>
   Vans Handbags E-4455
  </name>
  <category>
   Handbags
  </category>
  <size>
   M
  </size>
  <color>
   Фиолетовый
  </color>
  <material>
   Вискоза
  </material>
  <price>
   259764
  </price>
  <rating>
   1.07
  </rating>
  <reviews>
   864848
  </reviews>
  <exclusive>
   yes
  </exclusive>
  <sporty>
   yes
  </sporty>
 </clothing>
 <clothing>
  <id>
   856419897
  </id>
  <name>
   Brooks Umbrellas W-2404
  </name>
  <category>
   Umbrellas
  </category>
  <size>
   XL
  </size>
  <color>
   Голубой
  </color>
  <material>
   Хлопок
  </material>
  <price>
   959718
  </price>
  <rating>
   2.93
  </rating>
  <reviews>
   373695
  </reviews>
  <new>
   -
  </new>
  <exclusive>
   no
  </exclusive>
 </clothing>
 <clothing>
  <id>
   386186110
  </id>
  <name>
   Asics Umbrellas B-1146
  </name>
  <category>
   Umbrellas
  </category>
  <size>
   L
  </size>
  <color>
   Синий
  </color>
  <material>
   Полиэстер
  </material>
  <price>
   956305
  </price>
  <rating>
   3.54
  </rating>
  <reviews>
   402080
  </reviews>
  <new>
   -
  </new>
  <exclusive>
   no
  </exclusive>
 </clothing>
 <clothing>
  <id>
   570123358
  </id>
  <name>
   Lacoste Pants I-7901
  </name>
  <category>
   Pants
  </category>
  <size>
   XXL
  </size>
  <color>
   Фиолетовый
  </color>
  <material>
   Кожа
  </material>
  <price>
   943846
  </price>
  <rating>
   3.96
  </rating>
  <reviews>
   390581
  </reviews>
  <exclusive>
   yes
  </exclusive>
 </clothing>
 <clothing>
  <id>
   540712423
  </id>
  <name>
   Brooks T-shirt M-2612
  </name>
  <category>
   T-shirt
  </category>
  <size>
   L
  </size>
  <color>
   Синий
  </color>
  <material>
   Кожа
  </material>
  <price>
   320861
  </price>
  <rating>
   1.85
  </rating>
  <reviews>
   965850
  </reviews>
  <new>
   -
  </new>
  <exclusive>
   no
  </exclusive>
 </clothing>
 <clothing>
  <id>
   912257162
  </id>
  <name>
   Lacoste T-shirt W-1575
  </name>
  <category>
   T-shirt
  </category>
  <size>
   S
  </size>
  <color>
   Зеленый
  </color>
  <material>
   Шерсть
  </material>
  <price>
   799999
  </price>
  <rating>
   4.89
  </rating>
  <reviews>
   615443
  </reviews>
  <new>
   -
  </new>
  <exclusive>
   no
  </exclusive>
 </clothing>
 <clothing>
  <id>
   813689270
  </id>
  <name>
   Vans Belts U-2986
  </name>
  <category>
   Belts
  </category>
  <size>
   S
  </size>
  <color>
   Желтый
  </color>
  <material>
   Лен
  </material>
  <price>
   526751
  </price>
  <rating>
   4.0
  </rating>
  <reviews>
   565327
  </reviews>
  <new>
   -
  </new>
  <exclusive>
   no
  </exclusive>
 </clothing>
 <clothing>
  <id>
   236418601
  </id>
  <name>
   Lacoste Jeans S-7558
  </name>
  <category>
   Jeans
  </category>
  <size>
   S
  </size>
  <color>
   Оранжевый
  </color>
  <material>
   Нейлон
  </material>
  <price>
   680549
  </price>
  <rating>
   3.46
  </rating>
  <reviews>
   984429
  </reviews>
  <new>
   -
  </new>
  <exclusive>
   no
  </exclusive>
  <sporty>
   no
  </sporty>
 </clothing>
 <clothing>
  <id>
   801723521
  </id>
  <name>
   Adidas T-shirt J-5962
  </name>
  <category>
   T-shirt
  </category>
  <size>
   XL
  </size>
  <color>
   Зеленый
  </color>
  <material>
   Лен
  </material>
  <price>
   435106
  </price>
  <rating>
   4.03
  </rating>
  <reviews>
   788887
  </reviews>
  <new>
   -
  </new>
 </clothing>
 <clothing>
  <id>
   443892762
  </id>
  <name>
   Ellesse Umbrellas L-2588
  </name>
  <category>
   Umbrellas
  </category>
  <size>
   XXL
  </size>
  <color>
   Желтый
  </color>
  <material>
   Нейлон
  </material>
  <price>
   154699
  </price>
  <rating>
   4.16
  </rating>
  <reviews>
   542475
  </reviews>
  <exclusive>
   yes
  </exclusive>
  <sporty>
   no
  </sporty>
 </clothing>
 <clothing>
  <id>
   428042037
  </id>
  <name>
   Ellesse Shirt O-2907
  </name>
  <category>
   Shirt
  </category>
  <size>
   M
  </size>
  <color>
   Желтый
  </color>
  <material>
   Хлопок
  </material>
  <price>
   541524
  </price>
  <rating>
   2.93
  </rating>
  <reviews>
   233405
  </reviews>
  <new>
   +
  </new>
  <exclusive>
   no
  </exclusive>
  <sporty>
   yes
  </sporty>
 </clothing>
 <clothing>
  <id>
   387752493
  </id>
  <name>
   Ellesse Dress L-2228
  </name>
  <category>
   Dress
  </category>
  <size>
   XXL
  </size>
  <color>
   Зеленый
  </color>
  <material>
   Шерсть
  </material>
  <price>
   914284
  </price>
  <rating>
   4.16
  </rating>
  <reviews>
   58984
  </reviews>
  <new>
   +
  </new>
  <exclusive>
   yes
  </exclusive>
 </clothing>
 <clothing>
  <id>
   170366557
  </id>
  <name>
   Addidas Jacket Q-7030
  </name>
  <category>
   Jacket
  </category>
  <size>
   L
  </size>
  <color>
   Синий
  </color>
  <material>
   Шелк
  </material>
  <price>
   914749
  </price>
  <rating>
   3.98
  </rating>
  <reviews>
   58753
  </reviews>
  <new>
   -
  </new>
  <exclusive>
   yes
  </exclusive>
  <sporty>
   no
  </sporty>
 </clothing>
 <clothing>
  <id>
   910277189
  </id>
  <name>
   Reebok Jeans L-7989
  </name>
  <category>
   Jeans
  </category>
  <size>
   M
  </size>
  <color>
   Красный
  </color>
  <material>
   Шелк
  </material>
  <price>
   983724
  </price>
  <rating>
   1.49
  </rating>
  <reviews>
   520138
  </reviews>
  <new>
   -
  </new>
  <exclusive>
   no
  </exclusive>
 </clothing>
 <clothing>
  <id>
   541140380
  </id>
  <name>
   DC Jeans S-7025
  </name>
  <category>
   Jeans
  </category>
  <size>
   XXL
  </size>
  <color>
   Голубой
  </color>
  <material>
   Кожа
  </material>
  <price>
   832205
  </price>
  <rating>
   4.38
  </rating>
  <reviews>
   352180
  </reviews>
  <new>
   +
  </new>
  <exclusive>
   no
  </exclusive>
  <sporty>
   yes
  </sporty>
 </clothing>
 <clothing>
  <id>
   872279712
  </id>
  <name>
   Adidas Gloves D-3280
  </name>
  <category>
   Gloves
  </category>
  <size>
   M
  </size>
  <color>
   Желтый
  </color>
  <material>
   Нейлон
  </material>
  <price>
   231583
  </price>
  <rating>
   3.63
  </rating>
  <reviews>
   752204
  </reviews>
  <new>
   +
  </new>
  <exclusive>
   yes
  </exclusive>
 </clothing>
 <clothing>
  <id>
   971208721
  </id>
  <name>
   Lacoste Shoes Y-6132
  </name>
  <category>
   Shoes
  </category>
  <size>
   S
  </size>
  <color>
   Оранжевый
  </color>
  <material>
   Кожа
  </material>
  <price>
   379171
  </price>
  <rating>
   3.91
  </rating>
  <reviews>
   773822
  </reviews>
  <exclusive>
   no
  </exclusive>
 </clothing>
 <clothing>
  <id>
   799656482
  </id>
  <name>
   Vans Shoes K-6396
  </name>
  <category>
   Shoes
  </category>
  <size>
   M
  </size>
  <color>
   Голубой
  </color>
  <material>
   Кожа
  </material>
  <price>
   637001
  </price>
  <rating>
   3.18
  </rating>
  <reviews>
   520572
  </reviews>
  <new>
   -
  </new>
 </clothing>
 <clothing>
  <id>
   651568559
  </id>
  <name>
   Ellesse Umbrellas I-2336
  </name>
  <category>
   Umbrellas
  </category>
  <size>
   L
  </size>
  <color>
   Зеленый
  </color>
  <material>
   Хлопок
  </material>
  <price>
   548005
  </price>
  <rating>
   3.78
  </rating>
  <reviews>
   457152
  </reviews>
  <new>
   -
  </new>
 </clothing>
 <clothing>
  <id>
   908919354
  </id>
  <name>
   Addidas T-shirt F-4841
  </name>
  <category>
   T-shirt
  </category>
  <size>
   S
  </size>
  <color>
   Желтый
  </color>
  <material>
   Шерсть
  </material>
  <price>
   988486
  </price>
  <rating>
   4.21
  </rating>
  <reviews>
   734218
  </reviews>
  <new>
   -
  </new>
  <exclusive>
   no
  </exclusive>
  <sporty>
   yes
  </sporty>
 </clothing>
 <clothing>
  <id>
   656551528
  </id>
  <name>
   Under Armour Handbags Z-3457
  </name>
  <category>
   Handbags
  </category>
  <size>
   L
  </size>
  <color>
   Красный
  </color>
  <material>
   Шерсть
  </material>
  <price>
   124883
  </price>
  <rating>
   3.24
  </rating>
  <reviews>
   347543
  </reviews>
  <new>
   +
  </new>
  <exclusive>
   yes
  </exclusive>
  <sporty>
   yes
  </sporty>
 </clothing>
 <clothing>
  <id>
   258315717
  </id>
  <name>
   Reebok Dress K-4782
  </name>
  <category>
   Dress
  </category>
  <size>
   M
  </size>
  <color>
   Желтый
  </color>
  <material>
   Полиэстер
  </material>
  <price>
   262273
  </price>
  <rating>
   1.74
  </rating>
  <reviews>
   216501
  </reviews>
  <exclusive>
   yes
  </exclusive>
  <sporty>
   no
  </sporty>
 </clothing>
 <clothing>
  <id>
   442753315
  </id>
  <name>
   DC Dress P-5192
  </name>
  <category>
   Dress
  </category>
  <size>
   S
  </size>
  <color>
   Зеленый
  </color>
  <material>
   Шерсть
  </material>
  <price>
   308429
  </price>
  <rating>
   1.07
  </rating>
  <reviews>
   90802
  </reviews>
 </clothing>
 <clothing>
  <id>
   918324776
  </id>
  <name>
   Brooks Belts A-9464
  </name>
  <category>
   Belts
  </category>
  <size>
   L
  </size>
  <color>
   Синий
  </color>
  <material>
   Шерсть
  </material>
  <price>
   855246
  </price>
  <rating>
   4.19
  </rating>
  <reviews>
   122843
  </reviews>
  <new>
   +
  </new>
 </clothing>
 <clothing>
  <id>
   435910277
  </id>
  <name>
   Puma Belts E-4652
  </name>
  <category>
   Belts
  </category>
  <size>
   XL
  </size>
  <color>
   Фиолетовый
  </color>
  <material>
   Шелк
  </material>
  <price>
   728074
  </price>
  <rating>
   3.65
  </rating>
  <reviews>
   68690
  </reviews>
  <new>
   -
  </new>
 </clothing>
 <clothing>
  <id>
   743989910
  </id>
  <name>
   Addidas Blouse Q-7987
  </name>
  <category>
   Blouse
  </category>
  <size>
   S
  </size>
  <color>
   Фиолетовый
  </color>
  <material>
   Шелк
  </material>
  <price>
   890067
  </price>
  <rating>
   4.12
  </rating>
  <reviews>
   765003
  </reviews>
  <exclusive>
   no
  </exclusive>
  <sporty>
   no
  </sporty>
 </clothing>
 <clothing>
  <id>
   134135509
  </id>
  <name>
   Fila Hat F-4465
  </name>
  <category>
   Hat
  </category>
  <size>
   M
  </size>
  <color>
   Красный
  </color>
  <material>
   Лен
  </material>
  <price>
   612510
  </price>
  <rating>
   2.45
  </rating>
  <reviews>
   679132
  </reviews>
  <new>
   -
  </new>
  <exclusive>
   yes
  </exclusive>
 </clothing>
 <clothing>
  <id>
   940072661
  </id>
  <name>
   Nike Gloves W-4654
  </name>
  <category>
   Gloves
  </category>
  <size>
   M
  </size>
  <color>
   Красный
  </color>
  <material>
   Хлопок
  </material>
  <price>
   549874
  </price>
  <rating>
   3.09
  </rating>
  <reviews>
   195073
  </reviews>
  <new>
   -
  </new>
  <sporty>
   no
  </sporty>
 </clothing>
 <clothing>
  <id>
   696146149
  </id>
  <name>
   Ellesse Jacket D-1348
  </name>
  <category>
   Jacket
  </category>
  <size>
   M
  </size>
  <color>
   Желтый
  </color>
  <material>
   Шерсть
  </material>
  <price>
   125710
  </price>
  <rating>
   1.12
  </rating>
  <reviews>
   123188
  </reviews>
  <exclusive>
   no
  </exclusive>
  <sporty>
   no
  </sporty>
 </clothing>
 <clothing>
  <id>
   720865998
  </id>
  <name>
   Asics Skirt L-5059
  </name>
  <category>
   Skirt
  </category>
  <size>
   S
  </size>
  <color>
   Зеленый
  </color>
  <material>
   Шерсть
  </material>
  <price>
   761870
  </price>
  <rating>
   2.27
  </rating>
  <reviews>
   104654
  </reviews>
  <new>
   -
  </new>
  <exclusive>
   no
  </exclusive>
  <sporty>
   yes
  </sporty>
 </clothing>
 <clothing>
  <id>
   636541849
  </id>
  <name>
   DC Umbrellas T-8869
  </name>
  <category>
   Umbrellas
  </category>
  <size>
   L
  </size>
  <color>
   Синий
  </color>
  <material>
   Шерсть
  </material>
  <price>
   682057
  </price>
  <rating>
   1.71
  </rating>
  <reviews>
   99361
  </reviews>
  <new>
   +
  </new>
  <exclusive>
   yes
  </exclusive>
  <sporty>
   no
  </sporty>
 </clothing>
 <clothing>
  <id>
   176337913
  </id>
  <name>
   PleinSport T-shirt C-5227
  </name>
  <category>
   T-shirt
  </category>
  <size>
   XL
  </size>
  <color>
   Желтый
  </color>
  <material>
   Хлопок
  </material>
  <price>
   562829
  </price>
  <rating>
   4.72
  </rating>
  <reviews>
   161521
  </reviews>
  <exclusive>
   no
  </exclusive>
 </clothing>
 <clothing>
  <id>
   321307426
  </id>
  <name>
   Ellesse Blouse Q-4741
  </name>
  <category>
   Blouse
  </category>
  <size>
   S
  </size>
  <color>
   Красный
  </color>
  <material>
   Хлопок
  </material>
  <price>
   717019
  </price>
  <rating>
   4.36
  </rating>
  <reviews>
   170064
  </reviews>
  <new>
   -
  </new>
 </clothing>
 <clothing>
  <id>
   938328468
  </id>
  <name>
   Addidas Pants Q-9544
  </name>
  <category>
   Pants
  </category>
  <size>
   XXL
  </size>
  <color>
   Синий
  </color>
  <material>
   Шерсть
  </material>
  <price>
   374574
  </price>
  <rating>
   1.21
  </rating>
  <reviews>
   25326
  </reviews>
  <new>
   +
  </new>
  <sporty>
   no
  </sporty>
 </clothing>
 <clothing>
  <id>
   700572370
  </id>
  <name>
   Under Armour Socks X-1249
  </name>
  <category>
   Socks
  </category>
  <size>
   XXL
  </size>
  <color>
   Зеленый
  </color>
  <material>
   Кожа
  </material>
  <price>
   920888
  </price>
  <rating>
   4.17
  </rating>
  <reviews>
   451512
  </reviews>
  <new>
   -
  </new>
  <exclusive>
   no
  </exclusive>
  <sporty>
   yes
  </sporty>
 </clothing>
</clothing-items>
